pySpaceX/__init__.py
pySpaceX/space.py
pySpaceX/exceptions/__init__.py
pySpaceX/exceptions/exceptions.py
pySpaceX/methods/__init__.py
pySpaceX/methods/capsule.py
pySpaceX/methods/cores.py
pySpaceX/methods/crew.py
pySpaceX/methods/dragons.py
pySpaceX/methods/fairings.py
pySpaceX/methods/history.py
pySpaceX/methods/info.py
pySpaceX/methods/landing.py
pySpaceX/methods/launches.py
pySpaceX/methods/launchpad.py
pySpaceX/methods/missions.py
pySpaceX/methods/payloads.py
pySpaceX/methods/roadster.py
pySpaceX/methods/rockets.py
pySpaceX/methods/ships.py
pySpaceX/methods/starlink.py
tests/__init__.py
tests/test_space.py
pySpaceX-1.2.2.dist-info/LICENSE
pySpaceX-1.2.2.dist-info/METADATA
pySpaceX-1.2.2.dist-info/WHEEL
pySpaceX-1.2.2.dist-info/top_level.txt
pySpaceX-1.2.2.dist-info/RECORD
