Metadata-Version: 2.1
Name: pySpaceX
Version: 1.2.2
Summary: An unofficial python3 SpaceX API wrapper
Home-page: https://github.com/TwoSails/pySpaceX
Author: TwoSails
License: UNKNOWN
Platform: UNKNOWN
Classifier: Programming Language :: Python :: 3
Classifier: License :: OSI Approved :: GNU General Public License v3 (GPLv3) 
Classifier: Operating System :: OS Independent
Requires: requests
Requires-Python: >=3.6
License-File: LICENSE
